<?xml version="1.0" encoding="UTF-8"?>
<service>
    <id>AI.Enterprise.IntegrationService</id>
    <name>AI.Enterprise.IntegrationService</name>
    <description>PT AI EE Integration Service</description>
    <executable>java</executable>
    <arguments>-Xmx2g -Xms32m -XX:+UseConcMarkSweepGC -Dspring.main.lazy-initialization=true
        -Dlogging.level.com.ptsecurity.appsec.ai.ee.utils.ci.integration.service=TRACE -jar
        ptai-integration-service.jar 10
    </arguments>
    <startmode>Manual</startmode>
</service>