{"id":"f721129a-761a-4b46-ba24-bdf579bc570e","projectId":"c9821e12-d83d-4727-9664-12bd21866ff6","settingsId":"d6597c74-0fcf-4f46-9584-f9e98c0db699","scanDate":"2023-05-06T08:21:51.921667Z","progress":{"stage":"Done","subStage":null,"value":0},"statistic":{"high":4,"medium":3,"low":15,"potential":2,"total":24,"filesTotal":4,"filesScanned":4,"urlsScanned":0,"urlsTotal":0,"scanDuration":"00:00:11.9028590","policyState":"None"},"scanEnvironment":{"installatorVersion":{"type":"ApplicationInspector","version":"4.3.0.22105"}},"isRunFromQueue":true}