{"id":"4580e3b1-27cb-4870-abda-58c81c917036","projectId":"4f7d68e7-f50f-4677-88b8-4c0f775b6b60","settingsId":"3d6d2971-8404-4b4e-a425-1a34e53e8d61","scanDate":"2022-12-25T15:07:04.074536Z","progress":{"stage":"Done","subStage":null,"value":0},"statistic":{"high":26,"medium":39,"low":18,"potential":135,"total":218,"filesTotal":18,"filesScanned":18,"urlsScanned":0,"urlsTotal":0,"scanDuration":"00:01:35.0089990","policyState":"None"},"scanEnvironment":{"installatorVersion":{"type":"ApplicationInspector","version":"4.2.0.16733"}},"isRunFromQueue":false}